RAM/ram.vhd
library ieee;
use ieee.std_logic_1164.all;

entity ram is
  port (
        clk: in std_logic;
        write_enable: in std_logic;
        data_in: in std_logic_vector (7 downto 0);
        addr: in integer range 0 to 15;
        data_out: out std_logic_vector (7 downto 0));
end ram;

architecture seq of ram is
  type tableau_memoire is array (0 to 15) of std_logic_vector(7 downto 0);
  signal memoire : tableau_memoire;
begin
  process (clk)
  begin
    if rising_edge(clk) then
        if (write_enable='1') then --DEBUT ECRITURE
            memoire(addr) <= data_in;
        end if ;
    end if;
  end process;
  data_out <= memoire(addr); 
end architecture;

RAM/tb.vhd
library ieee;
use ieee.std_logic_1164.all;	   
use ieee.numeric_std.all;

entity tb is
end tb;

architecture seq of tb is
    	
   	signal clk			: std_logic;
    signal write_enable	: std_logic;
    signal data_in		: std_logic_vector (7 downto 0);
    signal addr			: integer range 0 to 15;
    signal data_out		: std_logic_vector (7 downto 0);

begin

  M: entity work.ram port map(clk,write_enable,data_in,addr,data_out);
  
  CLOCK: process
  begin
    clk<='0';
    wait for 50 ns;
    clk<='1';
    wait for 50 ns;
  end process;

  STIMULATE:process
  begin
    write_enable <= '1';
    addr <=3;
    data_in <= std_logic_vector(to_unsigned(50,8)); 
    wait for 100 ns;
    addr <=4;
    data_in <= std_logic_vector(to_unsigned(51,8)); 
    wait for 100 ns;
    addr <=5;
    data_in <= std_logic_vector(to_unsigned(52,8)); 
    wait for 100 ns;
    write_enable <= '0';
    data_in <= std_logic_vector(to_unsigned(0,8)); 
   	wait for 100 ns;
   	addr<=3;
   	wait for 100 ns;
   	addr<=4;
   	wait for 100 ns;
   	addr<=5; 
   	wait for 100 ns;
  end process;
  
  
end architecture;

RAM/tb.vcd
$date
  Mon Feb  7 11:30:55 2022
$end
$version
  GHDL v0
$end
$timescale
  1 fs
$end
$scope module standard $end
$upscope $end
$scope module std_logic_1164 $end
$upscope $end
$scope module numeric_std $end
$upscope $end
$scope module tb $end
$var reg 1 ! clk $end
$var reg 1 " write_enable $end
$var reg 8 # data_in[7:0] $end
$var integer 32 $ addr $end
$var reg 8 % data_out[7:0] $end
$scope module m $end
$var reg 1 & clk $end
$var reg 1 ' write_enable $end
$var reg 8 ( data_in[7:0] $end
$var integer 32 ) addr $end
$var reg 8 * data_out[7:0] $end
$comment memoire is not handled $end
$upscope $end
$upscope $end
$enddefinitions $end
#0
0!
1"
b00110010 #
b11 $
bUUUUUUUU %
0&
1'
b00110010 (
b11 )
bUUUUUUUU *
#50000000
1!
b00110010 %
1&
b00110010 *
#100000000
0!
b00110011 #
b100 $
bUUUUUUUU %
0&
b00110011 (
b100 )
bUUUUUUUU *
#150000000
1!
b00110011 %
1&
b00110011 *
#200000000
0!
b00110100 #
b101 $
bUUUUUUUU %
0&
b00110100 (
b101 )
bUUUUUUUU *
#250000000
1!
b00110100 %
1&
b00110100 *
#300000000
0!
0"
b00000000 #
0&
0'
b00000000 (
#350000000
1!
1&
#400000000
0!
b11 $
b00110010 %
0&
b11 )
b00110010 *
#450000000
1!
1&
#500000000
0!
b100 $
b00110011 %
0&
b100 )
b00110011 *
#550000000
1!
1&
#600000000
0!
b101 $
b00110100 %
0&
b101 )
b00110100 *
#650000000
1!
1&
#700000000
0!
1"
b00110010 #
b11 $
b00110010 %
0&
1'
b00110010 (
b11 )
b00110010 *
#750000000
1!
1&
#800000000
0!
b00110011 #
b100 $
b00110011 %
0&
b00110011 (
b100 )
b00110011 *
