CDCNT/CDCNT.vhd
library ieee;
use ieee.std_logic_1164.all;

entity cdcnt is
    port
    (
    clk : in std_logic;
    lc : in std_logic;
    ud : in std_logic;
    d : in integer range 0 to 9;
    cb : out std_logic;
    q: out integer range 0 to 9
    );
    
end entity;

architecture behavior of cdcnt is 
	signal cnt : integer range 0 to 9;
begin
	process(clk,lc,ud)
	begin
		if rising_edge(clk)then
			if lc = '0'then
				cnt <= d;
			else
				if ud = '1'then
					if cnt = 9 then
						cnt<=0;
						cb<='1';
					else
						cnt<=cnt+1;
						cb<='0';
					end if;
				else
					if cnt = 0 then
						cnt<=9;
						cb<='1';
					else
						cnt<=cnt-1;
						cb<='0';
					end if;
				end if;
			end if;
		end if;
	end process;
	q<=cnt;
end architecture;

CDCNT/tb.vhd
library ieee;
use ieee.std_logic_1164.all;	   
use ieee.numeric_std.all;

entity tb is
end tb;

architecture seq of tb is
  
  	signal clk : std_logic;
    signal lc  : std_logic;
    signal ud  : std_logic;
    signal d   : integer range 0 to 9;
    signal cb  : std_logic;
    signal q   : integer range 0 to 9;

begin

  UUT: entity work.cdcnt port map(clk, lc, ud, d, cb, q);
  
  CLOCK: process
  begin
    clk<='1';
    wait for 1 ns;
    clk<='0';
    wait for 1 ns;
  end process;

  LoadCount:process
  begin
    lc <= '0'; 
    wait for 10 ns;
    lc <= '1'; 
    wait for 100 ns;
    wait;
  end process;
  
  
  UpDown:process
  begin
    ud <= '0'; 
    wait for 50 ns;
    ud <= '1'; 
    wait for 50 ns;
    wait;
  end process;
  
   process
        begin
            d <=4; wait for 10 ns;
            d<= 0; wait for 0 ns;
            wait;
   end process;
  
  
  
end architecture;

CDCNT/tb.vcd
$date
  Mon Jan 24 16:36:21 2022
$end
$version
  GHDL v0
$end
$timescale
  1 fs
$end
$scope module standard $end
$upscope $end
$scope module std_logic_1164 $end
$upscope $end
$scope module numeric_std $end
$upscope $end
$scope module tb $end
$var reg 1 ! clk $end
$var reg 1 " lc $end
$var reg 1 # ud $end
$var integer 32 $ d $end
$var reg 1 % cb $end
$var integer 32 & q $end
$scope module uut $end
$var reg 1 ' clk $end
$var reg 1 ( lc $end
$var reg 1 ) ud $end
$var integer 32 * d $end
$var reg 1 + cb $end
$var integer 32 , q $end
$var integer 32 - cnt $end
$upscope $end
$upscope $end
$enddefinitions $end
#0
1!
0"
0#
b100 $
U%
b0 &
1'
0(
0)
b100 *
U+
b0 ,
b0 -
#1000000
0!
0'
#2000000
1!
b100 &
1'
b100 ,
b100 -
#3000000
0!
0'
#4000000
1!
1'
#5000000
0!
0'
#6000000
1!
1'
#7000000
0!
0'
#8000000
1!
1'
#9000000
0!
0'
#10000000
1!
1"
b0 $
0%
b11 &
1'
1(
b0 *
0+
b11 ,
b11 -
#11000000
0!
0'
#12000000
1!
b10 &
1'
b10 ,
b10 -
#13000000
0!
0'
#14000000
1!
b1 &
1'
b1 ,
b1 -
#15000000
0!
0'
#16000000
1!
b0 &
1'
b0 ,
b0 -
#17000000
0!
0'
#18000000
1!
1%
b1001 &
1'
1+
b1001 ,
b1001 -
#19000000
0!
0'
#20000000
1!
0%
b1000 &
1'
0+
b1000 ,
b1000 -
#21000000
0!
0'
#22000000
1!
b111 &
1'
b111 ,
b111 -
#23000000
0!
0'
#24000000
1!
b110 &
1'
b110 ,
b110 -
#25000000
0!
0'
#26000000
1!
b101 &
1'
b101 ,
b101 -
#27000000
0!
0'
#28000000
1!
b100 &
1'
b100 ,
b100 -
#29000000
0!
0'
#30000000
1!
b11 &
1'
b11 ,
b11 -
#31000000
0!
0'
#32000000
1!
b10 &
1'
b10 ,
b10 -
#33000000
0!
0'
#34000000
1!
b1 &
1'
b1 ,
b1 -
#35000000
0!
0'
#36000000
1!
b0 &
1'
b0 ,
b0 -
#37000000
0!
0'
#38000000
1!
1%
b1001 &
1'
1+
b1001 ,
b1001 -
#39000000
0!
0'
#40000000
1!
0%
b1000 &
1'
0+
b1000 ,
b1000 -
#41000000
0!
0'
#42000000
1!
b111 &
1'
b111 ,
b111 -
#43000000
0!
0'
#44000000
1!
b110 &
1'
b110 ,
b110 -
#45000000
0!
0'
#46000000
1!
b101 &
1'
b101 ,
b101 -
#47000000
0!
0'
#48000000
1!
b100 &
1'
b100 ,
b100 -
#49000000
0!
0'
#50000000
1!
1#
b101 &
1'
1)
b101 ,
b101 -
#51000000
0!
0'
#52000000
1!
b110 &
1'
b110 ,
b110 -
#53000000
0!
0'
#54000000
1!
b111 &
1'
b111 ,
b111 -
#55000000
0!
0'
#56000000
1!
b1000 &
1'
b1000 ,
b1000 -
#57000000
0!
0'
#58000000
1!
b1001 &
1'
b1001 ,
b1001 -
#59000000
0!
0'
#60000000
1!
1%
b0 &
1'
1+
b0 ,
b0 -
#61000000
0!
0'
#62000000
1!
0%
b1 &
1'
0+
b1 ,
b1 -
#63000000
0!
0'
#64000000
1!
b10 &
1'
b10 ,
b10 -
#65000000
0!
0'
#66000000
1!
b11 &
1'
b11 ,
b11 -
#67000000
0!
0'
#68000000
1!
b100 &
1'
b100 ,
b100 -
#69000000
0!
0'
#70000000
1!
b101 &
1'
b101 ,
b101 -
#71000000
0!
0'
#72000000
1!
b110 &
1'
b110 ,
b110 -
#73000000
0!
0'
#74000000
1!
b111 &
1'
b111 ,
b111 -
#75000000
0!
0'
#76000000
1!
b1000 &
1'
b1000 ,
b1000 -
#77000000
0!
0'
#78000000
1!
b1001 &
1'
b1001 ,
b1001 -
#79000000
0!
0'
#80000000
1!
1%
b0 &
1'
1+
b0 ,
b0 -
#81000000
0!
0'
#82000000
1!
0%
b1 &
1'
0+
b1 ,
b1 -
#83000000
0!
0'
#84000000
1!
b10 &
1'
b10 ,
b10 -
#85000000
0!
0'
#86000000
1!
b11 &
1'
b11 ,
b11 -
#87000000
0!
0'
#88000000
1!
b100 &
1'
b100 ,
b100 -
#89000000
0!
0'
#90000000
1!
b101 &
1'
b101 ,
b101 -
#91000000
0!
0'
#92000000
1!
b110 &
1'
b110 ,
b110 -
#93000000
0!
0'
#94000000
1!
b111 &
1'
b111 ,
b111 -
#95000000
0!
0'
#96000000
1!
b1000 &
1'
b1000 ,
b1000 -
#97000000
0!
0'
#98000000
1!
b1001 &
1'
b1001 ,
b1001 -
#99000000
0!
0'
#100000000
1!
1%
b0 &
1'
1+
b0 ,
b0 -
