SUMN/sumn.vhd
library ieee;
use ieee.std_logic_1164.all;
use ieee.numeric_std.all;

entity sumn is
	generic(width: natural; n: natural);
	port(	clk : std_logic;
			x: in signed(width-1 downto 0);
			y: out signed(width-1 downto 0));
end entity;

architecture seq of sumn is
	type t_mem is array(0 to n-2) of signed(width-1 downto 0);
	signal mem : t_mem;
	
	begin
	process(clk)
	variable tmp : signed(width-1 downto 0);
	begin
		if rising_edge(clk) then
			tmp:=x;
			for i in 0 to n-2 loop
				tmp := tmp + mem(i);
			end loop;
			y<=tmp;
			for i in n-2 downto 1 loop
				mem(i)<= mem(i-1);
			end loop;
			mem(0)<=x;
		end if;
	end process;
end architecture;

SUMN/tb.vhd
library ieee;
use ieee.std_logic_1164.all;
use ieee.numeric_std.all;

entity tb is
  end tb;
  
architecture behav of tb is
    
  constant a    : natural := 5;
  constant largeur : natural := 9;
  signal   x    : signed(largeur-1 downto 0);
  signal   y    : signed(largeur-1 downto 0);
  signal   clk  : std_logic;
      
begin

  UUT : entity work.sumn generic map (width=> largeur,n=> a) port map (clk, x,y);

  CLOCK : process
  begin
    clk<='0';
    wait for 5 ns;

    clk<='1';
    wait for 5 ns;
  end process;

  STIM : process

    type pattern_array is array(natural range <>) of integer;
    constant patterns : pattern_array := (0,2,4,6,-8,-6,4,-2,0,2,6,4,5,1,2,0,0,3,1,2,4,5,3,2);

  begin

    for i in patterns'range loop
      x <= to_signed(patterns(i),largeur);
      wait for 10 ns;
    end loop;

    assert false report "end of test" severity note;
    wait;
  end process;

end architecture;

SUMN/tb.vcd
$date
  Tue Feb  8 17:03:09 2022
$end
$version
  GHDL v0
$end
$timescale
  1 fs
$end
$scope module standard $end
$upscope $end
$scope module std_logic_1164 $end
$upscope $end
$scope module numeric_std $end
$upscope $end
$scope module tb $end
$var reg 9 ! x[8:0] $end
$var reg 9 " y[8:0] $end
$var reg 1 # clk $end
$scope module uut $end
$var reg 1 $ clk $end
$var reg 9 % x[8:0] $end
$var reg 9 & y[8:0] $end
$comment mem is not handled $end
$upscope $end
$upscope $end
$enddefinitions $end
#0
b000000000 !
bUUUUUUUUU "
0#
0$
b000000000 %
bUUUUUUUUU &
#5000000
bXXXXXXXXX "
1#
1$
bXXXXXXXXX &
#10000000
b000000010 !
0#
0$
b000000010 %
#15000000
1#
1$
#20000000
b000000100 !
0#
0$
b000000100 %
#25000000
1#
1$
#30000000
b000000110 !
0#
0$
b000000110 %
#35000000
1#
1$
#40000000
b111111000 !
0#
0$
b111111000 %
#45000000
b000000100 "
1#
1$
b000000100 &
#50000000
b111111010 !
0#
0$
b111111010 %
#55000000
b111111110 "
1#
1$
b111111110 &
#60000000
b000000100 !
0#
0$
b000000100 %
#65000000
b000000000 "
1#
1$
b000000000 &
#70000000
b111111110 !
0#
0$
b111111110 %
#75000000
b111111010 "
1#
1$
b111111010 &
#80000000
b000000000 !
0#
0$
b000000000 %
#85000000
b111110100 "
1#
1$
b111110100 &
#90000000
b000000010 !
0#
0$
b000000010 %
#95000000
b111111110 "
1#
1$
b111111110 &
#100000000
b000000110 !
0#
0$
b000000110 %
#105000000
b000001010 "
1#
1$
b000001010 &
#110000000
b000000100 !
0#
0$
b000000100 %
#115000000
1#
1$
#120000000
b000000101 !
0#
0$
b000000101 %
#125000000
b000010001 "
1#
1$
b000010001 &
#130000000
b000000001 !
0#
0$
b000000001 %
#135000000
b000010010 "
1#
1$
b000010010 &
#140000000
b000000010 !
0#
0$
b000000010 %
#145000000
1#
1$
#150000000
b000000000 !
0#
0$
b000000000 %
#155000000
b000001100 "
1#
1$
b000001100 &
#160000000
0#
0$
#165000000
b000001000 "
1#
1$
b000001000 &
#170000000
b000000011 !
0#
0$
b000000011 %
#175000000
b000000110 "
1#
1$
b000000110 &
#180000000
b000000001 !
0#
0$
b000000001 %
#185000000
1#
1$
#190000000
b000000010 !
0#
0$
b000000010 %
#195000000
1#
1$
#200000000
b000000100 !
0#
0$
b000000100 %
#205000000
b000001010 "
1#
1$
b000001010 &
#210000000
b000000101 !
0#
0$
b000000101 %
#215000000
b000001111 "
1#
1$
b000001111 &
#220000000
b000000011 !
0#
0$
b000000011 %
#225000000
1#
1$
#230000000
b000000010 !
0#
0$
b000000010 %
#235000000
b000010000 "
1#
1$
b000010000 &
#240000000
0#
0$
#245000000
1#
1$
#250000000
0#
0$
#255000000
b000001110 "
1#
1$
b000001110 &
#260000000
0#
0$
#265000000
b000001011 "
1#
1$
b000001011 &
#270000000
0#
0$
#275000000
b000001010 "
1#
1$
b000001010 &
