RECOG/recog.vhd
library ieee;
use ieee.std_logic_1164.all;
use ieee.numeric_std.all;

entity recog is
  port (e: in std_logic;
        h: in std_logic;
        rst: in std_logic;
        s: out std_logic);
end entity;

architecture beh of recog is
  signal cnt : integer range 0 to 3;
begin
  process (h,rst)
  begin
    if rst ='1' then --RAZ 
        cnt<=0;
    elsif rising_edge(h) then
        if e='1' then
            if cnt<3 then
                cnt <= cnt+1;
            end if ;
        else
            cnt <=0;
        end if;
    end if;
  end process;
s <= '1' when cnt >=3 else '0';
end architecture;

RECOG/tb.vhd
library ieee;
use ieee.std_logic_1164.all;	   
use ieee.numeric_std.all;

entity tb is
end tb;

architecture seq of tb is
    
    signal e 	:  std_logic;
   	signal h 	:  std_logic;
   	signal rst 	:  std_logic;
   	signal s 	:  std_logic;

begin

  UUT: entity work.recog port map(e, h, rst, s);
  
  CLOCK: process
  begin
    h<='0';
    wait for 5 ns;
    h<='1';
    wait for 5 ns;
  end process;

  RESET:process
  begin
    rst <= '1'; 
    wait for 1 ns;
   	rst <= '0'; 
    wait for 2 ns;
    wait;
  end process;
  
  
  ENTRE:process
  begin
    e <= '0'; 
    wait for 10 ns;
    e <= '1'; 
    wait for 10 ns;
    e <= '0'; 
    wait for 10 ns;
    e <= '1'; 
    wait for 20 ns;
    e <= '0'; 
    wait for 10 ns;
    e <= '1'; 
    wait for 30 ns;
    e <= '0'; 
    wait for 10 ns;
    e <= '1'; 
    wait for 40 ns;
    wait;
  end process; 
  
  
end architecture;

RECOG/tb.vcd
$date
  Mon Feb  7 10:34:12 2022
$end
$version
  GHDL v0
$end
$timescale
  1 fs
$end
$scope module standard $end
$upscope $end
$scope module std_logic_1164 $end
$upscope $end
$scope module numeric_std $end
$upscope $end
$scope module tb $end
$var reg 1 ! e $end
$var reg 1 " h $end
$var reg 1 # rst $end
$var reg 1 $ s $end
$scope module uut $end
$var reg 1 % e $end
$var reg 1 & h $end
$var reg 1 ' rst $end
$var reg 1 ( s $end
$var integer 32 ) cnt $end
$upscope $end
$upscope $end
$enddefinitions $end
#0
0!
0"
1#
0$
0%
0&
1'
0(
b0 )
#1000000
0#
0'
#3000000
#5000000
1"
1&
#10000000
1!
0"
1%
0&
#15000000
1"
1&
b1 )
#20000000
0!
0"
0%
0&
#25000000
1"
1&
b0 )
#30000000
1!
0"
1%
0&
#35000000
1"
1&
b1 )
#40000000
0"
0&
#45000000
1"
1&
b10 )
#50000000
0!
0"
0%
0&
#55000000
1"
1&
b0 )
#60000000
1!
0"
1%
0&
#65000000
1"
1&
b1 )
#70000000
0"
0&
#75000000
1"
1&
b10 )
#80000000
0"
0&
#85000000
1"
1$
1&
1(
b11 )
#90000000
0!
0"
0%
0&
#95000000
1"
0$
1&
0(
b0 )
#100000000
1!
0"
1%
0&
#105000000
1"
1&
b1 )
#110000000
0"
0&
#115000000
1"
1&
b10 )
#120000000
0"
0&
#125000000
1"
1$
1&
1(
b11 )
#130000000
0"
0&
#135000000
1"
1&
#140000000
0"
0&
#145000000
1"
1&
#150000000
0"
0&
#155000000
1"
1&
#160000000
0"
0&
#165000000
1"
1&
#170000000
0"
0&
#175000000
1"
1&
#180000000
0"
0&
#185000000
1"
1&
#190000000
0"
0&
#195000000
1"
1&
#200000000
0"
0&
