FIR/fir.vhd
library ieee;
use ieee.std_logic_1164.all;
use ieee.numeric_std.all;

entity fir3 is
  generic(width:natural);
  port (clk: in std_logic;
        x : in signed (width-1 downto 0);
        y : out signed (2*width-1 downto 0));
end entity;


	
architecture seq of fir3 is

    type cst_array is array(natural range <>) of integer;
    constant constante : cst_array := (3,2,1);
    
    signal z1 : signed(width -1 downto 0);
    signal z2 : signed(width -1 downto 0);
    
    
    
    function add_saturate(signal a : signed; signal b: signed) return signed is
		variable r: signed(width-1 downto 0);
		begin
			r := a+b;
			if(a(a'left) = b(b'left)) then 
				if(r(r'left) = a(a'left)) then
					return r;
				else
					r(r'left) := a(a'left);
					if(r(r'left) = '1') then
						r:= (others =>'0');
						r(r'left):= '1';
						return r;
					else
						r:= (others => '1');
						r(r'left):= '0';
						return r;
					end if;
				end if;
			else
				return r;
			end if;
	end;

    
    
    begin
    process(clk)
        begin
            if rising_edge(clk) then
                y <= to_signed(constante(0), width) * x + to_signed(constante(1), width) * z1 + to_signed(constante(2), width) * z2;
                z1 <= x;
                z2 <= z1;
            end if;
    end process;
end architecture;

FIR/tb.vhd
library ieee;
use ieee.std_logic_1164.all;
use ieee.numeric_std.all;

entity tb is
  end tb;
  
architecture behav of tb is

  constant largeur: natural := 4;
  signal clk : std_logic;
  signal   x    : signed(largeur-1 downto 0);
  signal   y    : signed(2*largeur-1 downto 0);
      
begin

  UUT : entity work.fir3 generic map (largeur) port map (clk, x,y);

  CLOCK : process
  begin
    clk<='0';
    wait for 5 ns;

    clk<='1';
    wait for 5 ns;
  end process;

  STIM : process

    type pattern_array is array(natural range <>) of integer;
    constant patterns : pattern_array := (0,2,4,6,-8,-6,4,-2,0);
  begin

    for i in patterns'range loop
      x <= to_signed(patterns(i),largeur);
      wait for 10 ns;
    end loop;

    assert false report "end of test" severity note;
    wait;
  end process;

end architecture;

FIR/tb.vcd
$date
  Wed Feb  9 11:59:38 2022
$end
$version
  GHDL v0
$end
$timescale
  1 fs
$end
$scope module standard $end
$upscope $end
$scope module std_logic_1164 $end
$upscope $end
$scope module numeric_std $end
$upscope $end
$scope module tb $end
$var reg 1 ! clk $end
$var reg 4 " x[3:0] $end
$var reg 8 # y[7:0] $end
$scope module uut $end
$var reg 1 $ clk $end
$var reg 4 % x[3:0] $end
$var reg 8 & y[7:0] $end
$var reg 4 ' z1[3:0] $end
$var reg 4 ( z2[3:0] $end
$upscope $end
$upscope $end
$enddefinitions $end
#0
0!
b0000 "
bUUUUUUUU #
0$
b0000 %
bUUUUUUUU &
bUUUU '
bUUUU (
#5000000
1!
b00000000 #
1$
b00000000 &
b0000 '
#10000000
0!
b0010 "
0$
b0010 %
#15000000
1!
b00000110 #
1$
b00000110 &
b0010 '
b0000 (
#20000000
0!
b0100 "
0$
b0100 %
#25000000
1!
b00010000 #
1$
b00010000 &
b0100 '
b0010 (
#30000000
0!
b0110 "
0$
b0110 %
#35000000
1!
b00011100 #
1$
b00011100 &
b0110 '
b0100 (
#40000000
0!
b1000 "
0$
b1000 %
#45000000
1!
b11111000 #
1$
b11111000 &
b1000 '
b0110 (
#50000000
0!
b1010 "
0$
b1010 %
#55000000
1!
b11100100 #
1$
b11100100 &
b1010 '
b1000 (
#60000000
0!
b0100 "
0$
b0100 %
#65000000
1!
b11111000 #
1$
b11111000 &
b0100 '
b1010 (
#70000000
0!
b1110 "
0$
b1110 %
#75000000
1!
b11111100 #
1$
b11111100 &
b1110 '
b0100 (
#80000000
0!
b0000 "
0$
b0000 %
#85000000
1!
b00000000 #
1$
b00000000 &
b0000 '
b1110 (
#90000000
0!
0$
#95000000
1!
b11111110 #
1$
b11111110 &
b0000 (
#100000000
0!
0$
#105000000
1!
b00000000 #
1$
b00000000 &
