SOM/som.vhd
library ieee;
use ieee.std_logic_1164.all;
use ieee.numeric_std.all;

entity sum2 is
	generic(width: natural);
	port(clk: in std_logic;
		 x:in signed(width-1 downto 0);
		 y: out signed(width-1 downto 0));
end entity;


architecture beh of sum2 is
  signal z : signed(width-1 downto 0);
begin
  process (clk)
  begin
  	if rising_edge(clk) then
  		y<= x + z;
  		z<= x;
  	end if;    
  end process;

end architecture;

SOM/tb.vhd
library ieee;
use ieee.std_logic_1164.all;
use ieee.numeric_std.all;

entity tb is
  end tb;
  
architecture behav of tb is
    
  constant n    : natural := 9;
  signal   x    : signed(n-1 downto 0);
  signal   y    : signed(n-1 downto 0);
  signal   clk  : std_logic;
      
begin

  UUT : entity work.sum2 generic map (n) port map (clk, x,y);

  CLOCK : process
  begin
    clk<='0';
    wait for 5 ns;

    clk<='1';
    wait for 5 ns;
  end process;

  STIM : process

    type pattern_array is array(natural range <>) of integer;
    constant patterns : pattern_array := (0,2,4,6,-8,-6,4,-2,0);

  begin

    for i in patterns'range loop
      x <= to_signed(patterns(i),n);
      wait for 10 ns;
    end loop;

    assert false report "end of test" severity note;
    wait;
  end process;

end architecture;

SOM/tb.vcd
$date
  Tue Feb  8 16:05:22 2022
$end
$version
  GHDL v0
$end
$timescale
  1 fs
$end
$scope module standard $end
$upscope $end
$scope module std_logic_1164 $end
$upscope $end
$scope module numeric_std $end
$upscope $end
$scope module tb $end
$var reg 9 ! x[8:0] $end
$var reg 9 " y[8:0] $end
$var reg 1 # clk $end
$scope module uut $end
$var reg 1 $ clk $end
$var reg 9 % x[8:0] $end
$var reg 9 & y[8:0] $end
$var reg 9 ' z[8:0] $end
$upscope $end
$upscope $end
$enddefinitions $end
#0
b000000000 !
bUUUUUUUUU "
0#
0$
b000000000 %
bUUUUUUUUU &
bUUUUUUUUU '
#5000000
bXXXXXXXXX "
1#
1$
bXXXXXXXXX &
b000000000 '
#10000000
b000000010 !
0#
0$
b000000010 %
#15000000
b000000010 "
1#
1$
b000000010 &
b000000010 '
#20000000
b000000100 !
0#
0$
b000000100 %
#25000000
b000000110 "
1#
1$
b000000110 &
b000000100 '
#30000000
b000000110 !
0#
0$
b000000110 %
#35000000
b000001010 "
1#
1$
b000001010 &
b000000110 '
#40000000
b111111000 !
0#
0$
b111111000 %
#45000000
b111111110 "
1#
1$
b111111110 &
b111111000 '
#50000000
b111111010 !
0#
0$
b111111010 %
#55000000
b111110010 "
1#
1$
b111110010 &
b111111010 '
#60000000
b000000100 !
0#
0$
b000000100 %
#65000000
b111111110 "
1#
1$
b111111110 &
b000000100 '
#70000000
b111111110 !
0#
0$
b111111110 %
#75000000
b000000010 "
1#
1$
b000000010 &
b111111110 '
#80000000
b000000000 !
0#
0$
b000000000 %
#85000000
b111111110 "
1#
1$
b111111110 &
b000000000 '
#90000000
0#
0$
#95000000
b000000000 "
1#
1$
b000000000 &
